.gitignore
README.md
sample.py
sample_ohlc.py
setup.cfg
setup.py
bitkub/__init__.py
bitkub/bitkub.py
bitkub/constants.py
bitkub/decorators.py
bitkub/error.py
bitkub/request.py
bitkub/tests.py
bitkub_v2.egg-info/PKG-INFO
bitkub_v2.egg-info/SOURCES.txt
bitkub_v2.egg-info/dependency_links.txt
bitkub_v2.egg-info/requires.txt
bitkub_v2.egg-info/top_level.txt