Metadata-Version: 2.4
Name: bitkub-v2
Version: 3.2.1
Summary: A Python library backward compatibility for Bitkub API v2 and latest Bitkub official API
Home-page: https://github.com/appcorner/bitkub
Author: appcorner
Author-email: appcorner@yahoo.com
License: MIT
Keywords: bitkub,bitkub-python,bitkub-python-sdk
Requires-Dist: requests
Dynamic: author
Dynamic: author-email
Dynamic: description
Dynamic: description-content-type
Dynamic: home-page
Dynamic: keywords
Dynamic: license
Dynamic: requires-dist
Dynamic: summary
